{
  "schema_version": "3.0",
  "publisher_version": "3.0.0",
  "generated_at": "2026-07-04T02:46:36Z",
  "data_as_of": "2026-07-04T02:38:39.344124+00:00",
  "bot": {
    "name": "Len Dawg",
    "instrument": "/MES (micro S&P futures)",
    "starting_equity": 6057.6,
    "current_equity": 6710.1,
    "days_live": 6
  },
  "headline": {
    "bot_equity_change_usd": 652.5,
    "bot_equity_change_pct": 0.107716,
    "account_change_usd": 652.5,
    "account_change_pct": 0.107716,
    "realized_trade_pnl_usd": -91.14,
    "cost_drift_usd": -743.64,
    "total_trades": 11,
    "wins": 4,
    "losses": 7,
    "win_rate": 0.3636
  },
  "daily": [
    {
      "date": "2026-07-02",
      "pnl_usd": 26.27,
      "trades": 2,
      "wins": 1,
      "losses": 1,
      "end_equity_usd": 6710.1
    },
    {
      "date": "2026-06-09",
      "pnl_usd": -19.99,
      "trades": 1,
      "wins": 0,
      "losses": 1,
      "end_equity_usd": 5823.19
    },
    {
      "date": "2026-06-08",
      "pnl_usd": -66.23,
      "trades": 2,
      "wins": 0,
      "losses": 2,
      "end_equity_usd": 5909.29
    },
    {
      "date": "2026-06-05",
      "pnl_usd": -39.99,
      "trades": 1,
      "wins": 0,
      "losses": 1,
      "end_equity_usd": 6039.51
    },
    {
      "date": "2026-06-04",
      "pnl_usd": 3.78,
      "trades": 3,
      "wins": 2,
      "losses": 1,
      "end_equity_usd": 6082.29
    },
    {
      "date": "2026-06-02",
      "pnl_usd": 5.02,
      "trades": 2,
      "wins": 1,
      "losses": 1,
      "end_equity_usd": 6062.0
    }
  ],
  "trades": [
    {
      "bracket_id": "BR-4e6034bb",
      "date": "2026-06-02",
      "entry_ts": "2026-06-02T14:12:30.992487+00:00",
      "exit_ts": "2026-06-02T14:35:02.236067+00:00",
      "side": "SHORT",
      "entry_price": 7609.0,
      "exit_price": 7613.5,
      "stop_price": 7613.5,
      "target_price": 7602.0,
      "qty": 1,
      "pnl_usd": -21.24,
      "sub_signal": "ORF",
      "regime": null
    },
    {
      "bracket_id": "BR-be323269",
      "date": "2026-06-02",
      "entry_ts": "2026-06-02T17:28:30.191086+00:00",
      "exit_ts": "2026-06-02T19:11:30.360409+00:00",
      "side": "LONG",
      "entry_price": 7617.25,
      "exit_price": 7622.75,
      "stop_price": 7613.25,
      "target_price": 7622.75,
      "qty": 1,
      "pnl_usd": 26.26,
      "sub_signal": "ORF",
      "regime": null
    },
    {
      "bracket_id": "BR-7953937d",
      "date": "2026-06-04",
      "entry_ts": "2026-06-04T14:25:32.665839+00:00",
      "exit_ts": "2026-06-04T15:07:32.676706+00:00",
      "side": "SHORT",
      "entry_price": 7569.75,
      "exit_price": 7576.75,
      "stop_price": 7576.75,
      "target_price": 7559.25,
      "qty": 1,
      "pnl_usd": -36.24,
      "sub_signal": "ORF",
      "regime": null
    },
    {
      "bracket_id": "BR-851392b1",
      "date": "2026-06-04",
      "entry_ts": "2026-06-04T19:07:32.485040+00:00",
      "exit_ts": "2026-06-04T19:14:32.730257+00:00",
      "side": "SHORT",
      "entry_price": 7608.5,
      "exit_price": 7605.0,
      "stop_price": 7611.0,
      "target_price": 7605.0,
      "qty": 1,
      "pnl_usd": 16.26,
      "sub_signal": "ORF",
      "regime": null
    },
    {
      "bracket_id": "BR-8bbf03b9",
      "date": "2026-06-04",
      "entry_ts": "2026-06-04T19:29:32.695188+00:00",
      "exit_ts": "2026-06-04T19:45:40.512942+00:00",
      "side": "SHORT",
      "entry_price": 7609.25,
      "exit_price": 7605.75,
      "stop_price": 7611.75,
      "target_price": 7605.75,
      "qty": 1,
      "pnl_usd": 23.76,
      "sub_signal": "ORF",
      "regime": null
    },
    {
      "bracket_id": "BR-7447b855",
      "date": "2026-06-05",
      "entry_ts": "2026-06-05T15:39:33.585774+00:00",
      "exit_ts": "2026-06-05T16:02:33.401135+00:00",
      "side": "LONG",
      "entry_price": 7493.5,
      "exit_price": 7485.0,
      "stop_price": 7485.0,
      "target_price": 7506.0,
      "qty": 1,
      "pnl_usd": -39.99,
      "sub_signal": "ORF",
      "regime": null
    },
    {
      "bracket_id": "BR-4f73dc1d",
      "date": "2026-06-08",
      "entry_ts": "2026-06-08T17:02:32.276201+00:00",
      "exit_ts": "2026-06-08T17:04:02.025669+00:00",
      "side": "LONG",
      "entry_price": 7434.75,
      "exit_price": 7426.5,
      "stop_price": 7426.75,
      "target_price": 7446.75,
      "qty": 1,
      "pnl_usd": -28.74,
      "sub_signal": "ORF",
      "regime": null
    },
    {
      "bracket_id": "BR-6372224b",
      "date": "2026-06-08",
      "entry_ts": "2026-06-08T19:11:32.811535+00:00",
      "exit_ts": "2026-06-08T19:15:33.018965+00:00",
      "side": "LONG",
      "entry_price": 7420.5,
      "exit_price": 7413.0,
      "stop_price": 7413.0,
      "target_price": 7431.5,
      "qty": 1,
      "pnl_usd": -37.49,
      "sub_signal": "ORF",
      "regime": null
    },
    {
      "bracket_id": "BR-962b2c40",
      "date": "2026-06-09",
      "entry_ts": "2026-06-09T14:14:32.174072+00:00",
      "exit_ts": "2026-06-09T14:15:54.816125+00:00",
      "side": "LONG",
      "entry_price": 7445.75,
      "exit_price": 7434.5,
      "stop_price": 7434.0,
      "target_price": 7463.25,
      "qty": 1,
      "pnl_usd": -19.99,
      "sub_signal": "ORF",
      "regime": null
    },
    {
      "bracket_id": "BR-d726babd",
      "date": "2026-07-02",
      "entry_ts": "2026-07-02T14:44:32.319543+00:00",
      "exit_ts": "2026-07-02T15:01:46.414999+00:00",
      "side": "LONG",
      "entry_price": 7545.25,
      "exit_price": 7558.25,
      "stop_price": 7536.25,
      "target_price": 7558.25,
      "qty": 1,
      "pnl_usd": 63.76,
      "sub_signal": "ORF",
      "regime": null
    },
    {
      "bracket_id": "BR-c851ebe6",
      "date": "2026-07-02",
      "entry_ts": "2026-07-02T18:53:32.659851+00:00",
      "exit_ts": "2026-07-02T19:54:35.318281+00:00",
      "side": "SHORT",
      "entry_price": 7514.75,
      "exit_price": 7522.75,
      "stop_price": 7522.5,
      "target_price": 7502.75,
      "qty": 1,
      "pnl_usd": -37.49,
      "sub_signal": "ORF",
      "regime": null
    }
  ],
  "open_positions_detail": [
    {
      "symbol": "AAON",
      "shares": 1,
      "sleeve_id": "IWM100_R5H12_1SH_MR",
      "cohort_id": "IWM100_R5H12_1SH_MR:AAON:2026-07-02",
      "opened_date": "2026-07-02",
      "scheduled_exit_date": "2026-07-21",
      "entry_price": 107.62,
      "source": "cohort"
    },
    {
      "symbol": "COCO",
      "shares": 1,
      "sleeve_id": "IWM100_R5H12_1SH_MR",
      "cohort_id": "IWM100_R5H12_1SH_MR:COCO:2026-06-29",
      "opened_date": "2026-06-29",
      "scheduled_exit_date": "2026-07-16",
      "entry_price": 72.53,
      "source": "cohort"
    },
    {
      "symbol": "RMBS",
      "shares": 1,
      "sleeve_id": "IWM100_R5H12_1SH_MR",
      "cohort_id": "IWM100_R5H12_1SH_MR:RMBS:2026-06-29",
      "opened_date": "2026-06-29",
      "scheduled_exit_date": "2026-07-16",
      "entry_price": 123.9,
      "source": "cohort"
    },
    {
      "symbol": "SMCI",
      "shares": 1,
      "sleeve_id": "IWM100_R5H12_1SH_MR",
      "cohort_id": "IWM100_R5H12_1SH_MR:SMCI:2026-06-29",
      "opened_date": "2026-06-29",
      "scheduled_exit_date": "2026-07-16",
      "entry_price": 28.15,
      "source": "cohort"
    }
  ],
  "data_quality": {
    "warnings": [
      "realized trade P&L: -$91.14; bot-tracked equity change: $652.50; gap: -$743.64 in fees/slippage the bot did not capture per-trade",
      "1 bracket(s) submitted but never closed in journal — likely orphans from a prior crash"
    ],
    "orphan_closes": 0,
    "open_positions": 1
  },
  "_provenance": {
    "source": "quant-bot",
    "source_detail": "live/2026-07-03.jsonl",
    "data_as_of": "2026-07-04T02:38:39Z",
    "publisher_run_id": "7d88c832-7796-4530-aa1f-5f837ef5c349"
  }
}
